entitled/__init__.py
entitled/client.py
entitled/exceptions.py
entitled/policies.py
entitled/py.typed
entitled/response.py
entitled/rules.py
entitled-1.0.0.dist-info/METADATA
entitled-1.0.0.dist-info/WHEEL
entitled-1.0.0.dist-info/RECORD
