Metadata-Version: 2.4
Name: entitled
Version: 1.0.0
Summary: A library to make writing, enforcing and auditing your authorization policies a breeze
Author-email: Mathias Bigaignon <m.bigaignon@xefi.fr>
Requires-Python: <3.13,>=3.12
